[
  {
    "text": "할",
    "startMs": 100,
    "endMs": 967,
    "timestampMs": 100,
    "confidence": null
  },
  {
    "text": " 엘로드는",
    "startMs": 967,
    "endMs": 1833,
    "timestampMs": 967,
    "confidence": null
  },
  {
    "text": " 단언합니다.",
    "startMs": 1833,
    "endMs": 2700,
    "timestampMs": 1833,
    "confidence": null
  },
  {
    "text": "아침",
    "startMs": 2650,
    "endMs": 3465,
    "timestampMs": 2650,
    "confidence": null
  },
  {
    "text": " 1시간이",
    "startMs": 3465,
    "endMs": 4280,
    "timestampMs": 3465,
    "confidence": null
  },
  {
    "text": " 나머지",
    "startMs": 4280,
    "endMs": 5095,
    "timestampMs": 4280,
    "confidence": null
  },
  {
    "text": " 23시간을",
    "startMs": 5095,
    "endMs": 5910,
    "timestampMs": 5095,
    "confidence": null
  },
  {
    "text": " 결정한다고.",
    "startMs": 5910,
    "endMs": 6725,
    "timestampMs": 5910,
    "confidence": null
  },
  {
    "text": "하루의",
    "startMs": 6725,
    "endMs": 7420,
    "timestampMs": 6725,
    "confidence": null
  },
  {
    "text": " 첫",
    "startMs": 7420,
    "endMs": 8115,
    "timestampMs": 7420,
    "confidence": null
  },
  {
    "text": " 1시간에",
    "startMs": 8115,
    "endMs": 8809,
    "timestampMs": 8115,
    "confidence": null
  },
  {
    "text": " 어떤",
    "startMs": 8809,
    "endMs": 9504,
    "timestampMs": 8809,
    "confidence": null
  },
  {
    "text": " 습관을",
    "startMs": 9504,
    "endMs": 10199,
    "timestampMs": 9504,
    "confidence": null
  },
  {
    "text": " 실천하느냐가",
    "startMs": 10199,
    "endMs": 10894,
    "timestampMs": 10199,
    "confidence": null
  },
  {
    "text": " 그날",
    "startMs": 10894,
    "endMs": 11588,
    "timestampMs": 10894,
    "confidence": null
  },
  {
    "text": " 전체의",
    "startMs": 11588,
    "endMs": 12283,
    "timestampMs": 11588,
    "confidence": null
  },
  {
    "text": " 생산성,",
    "startMs": 12283,
    "endMs": 12978,
    "timestampMs": 12283,
    "confidence": null
  },
  {
    "text": " 에너지,",
    "startMs": 12978,
    "endMs": 13673,
    "timestampMs": 12978,
    "confidence": null
  },
  {
    "text": " 마인드셋을",
    "startMs": 13673,
    "endMs": 14367,
    "timestampMs": 13673,
    "confidence": null
  },
  {
    "text": " 좌우합니다.",
    "startMs": 14367,
    "endMs": 15062,
    "timestampMs": 14367,
    "confidence": null
  },
  {
    "text": "이것은",
    "startMs": 15062,
    "endMs": 15798,
    "timestampMs": 15062,
    "confidence": null
  },
  {
    "text": " 의지력의",
    "startMs": 15798,
    "endMs": 16533,
    "timestampMs": 15798,
    "confidence": null
  },
  {
    "text": " 문제가",
    "startMs": 16533,
    "endMs": 17269,
    "timestampMs": 16533,
    "confidence": null
  },
  {
    "text": " 아니라",
    "startMs": 17269,
    "endMs": 18004,
    "timestampMs": 17269,
    "confidence": null
  },
  {
    "text": " 시스템의",
    "startMs": 18004,
    "endMs": 18740,
    "timestampMs": 18004,
    "confidence": null
  },
  {
    "text": " 문제입니다.",
    "startMs": 18740,
    "endMs": 19475,
    "timestampMs": 18740,
    "confidence": null
  }
]