{
  "captions": [
    {
      "text": "정리하겠습니다.",
      "startMs": null,
      "endMs": null,
      "timestampMs": null,
      "confidence": null
    },
    {
      "text": " 스타트업",
      "startMs": null,
      "endMs": null,
      "timestampMs": null,
      "confidence": null
    },
    {
      "text": " 설계자는",
      "startMs": null,
      "endMs": null,
      "timestampMs": null,
      "confidence": null
    },
    {
      "text": " 단순한",
      "startMs": null,
      "endMs": null,
      "timestampMs": null,
      "confidence": null
    },
    {
      "text": " 마케팅",
      "startMs": null,
      "endMs": null,
      "timestampMs": null,
      "confidence": null
    },
    {
      "text": " 책이",
      "startMs": null,
      "endMs": null,
      "timestampMs": null,
      "confidence": null
    },
    {
      "text": " 아닙니다.",
      "startMs": null,
      "endMs": null,
      "timestampMs": null,
      "confidence": null
    },
    {
      "text": " 제품을",
      "startMs": null,
      "endMs": null,
      "timestampMs": null,
      "confidence": null
    },
    {
      "text": " 세상에",
      "startMs": null,
      "endMs": null,
      "timestampMs": null,
      "confidence": null
    },
    {
      "text": " 내놓는",
      "startMs": null,
      "endMs": null,
      "timestampMs": null,
      "confidence": null
    },
    {
      "text": " 방법을",
      "startMs": null,
      "endMs": null,
      "timestampMs": null,
      "confidence": null
    },
    {
      "text": " 완전히",
      "startMs": null,
      "endMs": null,
      "timestampMs": null,
      "confidence": null
    },
    {
      "text": " 바꾸는",
      "startMs": null,
      "endMs": null,
      "timestampMs": null,
      "confidence": null
    },
    {
      "text": " 설계도입니다.",
      "startMs": null,
      "endMs": null,
      "timestampMs": null,
      "confidence": null
    },
    {
      "text": " 론칭은",
      "startMs": null,
      "endMs": null,
      "timestampMs": null,
      "confidence": null
    },
    {
      "text": " 이벤트가",
      "startMs": null,
      "endMs": null,
      "timestampMs": null,
      "confidence": null
    },
    {
      "text": " 아니라",
      "startMs": null,
      "endMs": null,
      "timestampMs": null,
      "confidence": null
    },
    {
      "text": " 프로세스이고",
      "startMs": null,
      "endMs": null,
      "timestampMs": null,
      "confidence": null
    },
    {
      "text": " 사이드",
      "startMs": null,
      "endMs": null,
      "timestampMs": null,
      "confidence": null
    },
    {
      "text": " 웨이스",
      "startMs": null,
      "endMs": null,
      "timestampMs": null,
      "confidence": null
    },
    {
      "text": " 레터로",
      "startMs": null,
      "endMs": null,
      "timestampMs": null,
      "confidence": null
    },
    {
      "text": " 가치를",
      "startMs": null,
      "endMs": null,
      "timestampMs": null,
      "confidence": null
    },
    {
      "text": " 먼저",
      "startMs": null,
      "endMs": null,
      "timestampMs": null,
      "confidence": null
    },
    {
      "text": " 제공하며",
      "startMs": null,
      "endMs": null,
      "timestampMs": null,
      "confidence": null
    },
    {
      "text": " 시드론칭으로",
      "startMs": null,
      "endMs": null,
      "timestampMs": null,
      "confidence": null
    },
    {
      "text": " 아무것도",
      "startMs": null,
      "endMs": null,
      "timestampMs": null,
      "confidence": null
    },
    {
      "text": " 없는",
      "startMs": null,
      "endMs": null,
      "timestampMs": null,
      "confidence": null
    },
    {
      "text": " 상태에서도",
      "startMs": null,
      "endMs": null,
      "timestampMs": null,
      "confidence": null
    },
    {
      "text": " 시작할",
      "startMs": null,
      "endMs": null,
      "timestampMs": null,
      "confidence": null
    },
    {
      "text": " 수",
      "startMs": null,
      "endMs": null,
      "timestampMs": null,
      "confidence": null
    },
    {
      "text": " 있습니다.",
      "startMs": null,
      "endMs": null,
      "timestampMs": null,
      "confidence": null
    },
    {
      "text": " 완벽한",
      "startMs": null,
      "endMs": null,
      "timestampMs": null,
      "confidence": null
    },
    {
      "text": " 제품보다",
      "startMs": null,
      "endMs": null,
      "timestampMs": null,
      "confidence": null
    },
    {
      "text": " 당신의",
      "startMs": null,
      "endMs": null,
      "timestampMs": null,
      "confidence": null
    },
    {
      "text": " 이야기를",
      "startMs": null,
      "endMs": null,
      "timestampMs": null,
      "confidence": null
    },
    {
      "text": " 기다리는",
      "startMs": null,
      "endMs": null,
      "timestampMs": null,
      "confidence": null
    },
    {
      "text": " 100명이",
      "startMs": null,
      "endMs": null,
      "timestampMs": null,
      "confidence": null
    },
    {
      "text": " 먼저입니다.",
      "startMs": null,
      "endMs": null,
      "timestampMs": null,
      "confidence": null
    }
  ],
  "durationMs": 21504,
  "beatTimings": [
    {
      "beatId": "recap-b1",
      "resolvedStartFrame": null,
      "resolvedEndFrame": null,
      "originalStartRatio": 0,
      "originalEndRatio": 0.35
    },
    {
      "beatId": "recap-b2",
      "resolvedStartFrame": null,
      "resolvedEndFrame": null,
      "originalStartRatio": 0.35,
      "originalEndRatio": 1
    }
  ]
}